Metadata-Version: 1.2
Name: machinebox-python-sdk
Version: 0.1
Summary: Tools for working with Machinebox
Home-page: https://github.com/machinebox/machinebox-python-sdk
Author: Robin Cole
Author-email: robmarkcole@gmail.com
License: Apache License, Version 2.0
Keywords: machinebox
Platform: UNKNOWN
Classifier: Intended Audience :: Developers
Classifier: Natural Language :: English
Classifier: Programming Language :: Python
Classifier: Programming Language :: Python :: 3
Requires-Python: >=3.6
